alpha/__init__.py
alpha/cli.py
alpha/encoder.py
alpha/exceptions.py
alpha/py.typed
alpha/adapters/__init__.py
alpha/adapters/sqla_unit_of_work.py
alpha/containers/__init__.py
alpha/containers/container.py
alpha/domain/__init__.py
alpha/domain/models/__init__.py
alpha/domain/models/base_model.py
alpha/domain/models/life_cycle_base.py
alpha/domain/models/user.py
alpha/factories/__init__.py
alpha/factories/_type_conversion_matrix.py
alpha/factories/_type_mapping.py
alpha/factories/class_factories.py
alpha/factories/default_field_factory.py
alpha/factories/field_iterator.py
alpha/factories/jwt_factory.py
alpha/factories/logging_handler_factory.py
alpha/factories/model_class_factory.py
alpha/factories/request_factory.py
alpha/factories/response_factory.py
alpha/factories/type_factories.py
alpha/factories/models/__init__.py
alpha/factories/models/factory_classes.py
alpha/handlers/__init__.py
alpha/handlers/api_generate_handler.py
alpha/handlers/api_run_handler.py
alpha/handlers/base_handler.py
alpha/handlers/gen-code.sh
alpha/handlers/run-api.sh
alpha/handlers/models/__init__.py
alpha/handlers/models/argument.py
alpha/handlers/models/command.py
alpha/handlers/models/section.py
alpha/handlers/models/subparser.py
alpha/handlers/templates/__init__.py
alpha/handlers/templates/python-flask/Dockerfile.mustache
alpha/handlers/templates/python-flask/README.mustache
alpha/handlers/templates/python-flask/__init__model.mustache
alpha/handlers/templates/python-flask/__init__test.mustache
alpha/handlers/templates/python-flask/__main__.mustache
alpha/handlers/templates/python-flask/base_model.mustache
alpha/handlers/templates/python-flask/controller.mustache
alpha/handlers/templates/python-flask/controller_test.mustache
alpha/handlers/templates/python-flask/dockerignore.mustache
alpha/handlers/templates/python-flask/encoder.mustache
alpha/handlers/templates/python-flask/git_push.sh.mustache
alpha/handlers/templates/python-flask/gitignore.mustache
alpha_python-0.2.5.dist-info/licenses/LICENSE
alpha_python-0.2.5.dist-info/METADATA
alpha_python-0.2.5.dist-info/WHEEL
alpha_python-0.2.5.dist-info/entry_points.txt
alpha_python-0.2.5.dist-info/top_level.txt
alpha_python-0.2.5.dist-info/RECORD
